capella/__init__.py
capella/__main__.py
capella/gui_pages/__init__.py
capella/gui_pages/azimuth_page.py
capella/gui_pages/fit_slope_page.py
capella/gui_pages/lop_plot_page.py
capella/gui_pages/sight_entry_page.py
capella/gui_pages/sight_planning_page.py
capella/gui_pages/splash_page.py
capella/text_files/__init__.py
capella/text_files/sight_log.txt
capella/text_files/splash_text.txt
capella/text_files/tooltips.txt
capella/utilities/__init__.py
capella/utilities/autocompletion.py
capella/utilities/celestial_engine.py
capella/utilities/dead_reckoning.py
capella/utilities/ephemeris_calc.py
capella/utilities/input_checking.py
capella/utilities/os_handler.py
capella/utilities/reduce_sight.py
capella/utilities/sight_handling.py
capella/utilities/sight_planning.py
capella/utilities/tooltips.py
capella/utilities/utility_funcs.py
Capella-2.3.6.dist-info/LICENSE
Capella-2.3.6.dist-info/METADATA
Capella-2.3.6.dist-info/WHEEL
Capella-2.3.6.dist-info/entry_points.txt
Capella-2.3.6.dist-info/top_level.txt
Capella-2.3.6.dist-info/RECORD
