Metadata-Version: 2.1
Name: Capella
Version: 2.3.6
Summary: A Python package for celestial navigation
Home-page: https://github.com/AlexSpradling/Capella
Author: Alex Spradling
Author-email: alexspradling@gmail.com
Classifier: Programming Language :: Python :: 3
Classifier: License :: OSI Approved :: MIT License
License-File: LICENSE
Requires-Dist: skyfield
Requires-Dist: pandas
Requires-Dist: matplotlib
Requires-Dist: tabulate
Requires-Dist: scipy
Requires-Dist: ttkwidgets
Requires-Dist: pyperclip
Requires-Dist: geomag
Requires-Dist: ttkbootstrap
